LICENSE
MANIFEST.in
Makefile
README.md
requirements.txt
setup.cfg
setup.py
penapi/__init__.py
penapi/base_api.py
penapi/constants.py
penapi/files_api.py
penapi/pentaho.py
penapi/roles_api.py
penapi/users_api.py
pentaho_rest_api.egg-info/PKG-INFO
pentaho_rest_api.egg-info/SOURCES.txt
pentaho_rest_api.egg-info/dependency_links.txt
pentaho_rest_api.egg-info/entry_points.txt
pentaho_rest_api.egg-info/requires.txt
pentaho_rest_api.egg-info/top_level.txt