Metadata-Version: 1.1
Name: pentaho-rest-api
Version: 1.0.20
Summary: Python library for the pentaho BA REST API
Home-page: https://github.com/AlayaCare/pentaho-rest-api
Author: Saqib Khalil Yawar
Author-email: saqib.yawar@alayacare.com
License: UNKNOWN
Keywords: pentaho rest api development
Platform: UNKNOWN
Classifier: Development Status :: 3 - Alpha
Classifier: Intended Audience :: Developers
Classifier: Topic :: Software Development :: Build Tools
Classifier: Programming Language :: Python
Classifier: Programming Language :: Python :: 2.7
Classifier: License :: OSI Approved :: GNU General Public License (GPL)
